sqlobjects/__init__.py
sqlobjects/_install_rules.py
sqlobjects/cascade.py
sqlobjects/exceptions.py
sqlobjects/metadata.py
sqlobjects/mixins.py
sqlobjects/model.py
sqlobjects/queryset.py
sqlobjects/session.py
sqlobjects/signals.py
sqlobjects/validators.py
sqlobjects/database/__init__.py
sqlobjects/database/config.py
sqlobjects/database/manager.py
sqlobjects/expressions/__init__.py
sqlobjects/expressions/aggregate.py
sqlobjects/expressions/base.py
sqlobjects/expressions/function.py
sqlobjects/expressions/mixins.py
sqlobjects/expressions/scalar.py
sqlobjects/expressions/subquery.py
sqlobjects/expressions/terminal.py
sqlobjects/fields/__init__.py
sqlobjects/fields/core.py
sqlobjects/fields/functions.py
sqlobjects/fields/proxies.py
sqlobjects/fields/shortcuts.py
sqlobjects/fields/utils.py
sqlobjects/fields/relations/__init__.py
sqlobjects/fields/relations/descriptors.py
sqlobjects/fields/relations/managers.py
sqlobjects/fields/relations/prefetch.py
sqlobjects/fields/relations/strategies.py
sqlobjects/fields/relations/utils.py
sqlobjects/fields/types/__init__.py
sqlobjects/fields/types/base.py
sqlobjects/fields/types/comparators.py
sqlobjects/fields/types/registry.py
sqlobjects/internal/__init__.py
sqlobjects/internal/operations.py
sqlobjects/internal/results.py
sqlobjects/objects/__init__.py
sqlobjects/objects/bulk.py
sqlobjects/objects/core.py
sqlobjects/objects/upsert.py
sqlobjects/queries/__init__.py
sqlobjects/queries/builder.py
sqlobjects/queries/dialect.py
sqlobjects/queries/executor.py
sqlobjects/utils/__init__.py
sqlobjects/utils/inspect.py
sqlobjects/utils/naming.py
sqlobjects/utils/pattern.py
sqlobjects-1.0.16.data/data/share/sqlobjects/rules/01-database-session-guide.md
sqlobjects-1.0.16.data/data/share/sqlobjects/rules/02-model-definition-guide.md
sqlobjects-1.0.16.data/data/share/sqlobjects/rules/03-query-operations-guide.md
sqlobjects-1.0.16.data/data/share/sqlobjects/rules/04-crud-operations-guide.md
sqlobjects-1.0.16.dist-info/licenses/LICENSE
sqlobjects-1.0.16.dist-info/METADATA
sqlobjects-1.0.16.dist-info/WHEEL
sqlobjects-1.0.16.dist-info/entry_points.txt
sqlobjects-1.0.16.dist-info/top_level.txt
sqlobjects-1.0.16.dist-info/RECORD
