Metadata-Version: 2.4
Name: sqlobjects
Version: 1.0.16
Summary: Django-style async ORM library based on SQLAlchemy with chainable queries, Q objects, and relationship loading
Author-email: XtraVisions <gitadmin@xtravisions.com>, Chen Hao <chenhao@xtravisions.com>
Maintainer-email: XtraVisions <gitadmin@xtravisions.com>, Chen Hao <chenhao@xtravisions.com>
License-Expression: MIT
Project-URL: Homepage, https://github.com/XtraVisionsAI/sqlobjects
Project-URL: Repository, https://github.com/XtraVisionsAI/sqlobjects.git
Project-URL: Documentation, https://github.com/XtraVisionsAI/sqlobjects#readme
Project-URL: Bug Tracker, https://github.com/XtraVisionsAI/sqlobjects/issues
Project-URL: Changelog, https://github.com/XtraVisionsAI/sqlobjects/blob/main/CHANGELOG.md
Keywords: python,orm,async,django-style,database,query
Classifier: Development Status :: 4 - Beta
Classifier: Intended Audience :: Developers
Classifier: Operating System :: OS Independent
Classifier: Programming Language :: Python :: 3
Classifier: Programming Language :: Python :: 3.12
Classifier: Programming Language :: Python :: 3 :: Only
Classifier: Topic :: Database
Classifier: Topic :: Software Development :: Libraries :: Python Modules
Classifier: Framework :: AsyncIO
Classifier: Typing :: Typed
Requires-Python: >=3.12
License-File: LICENSE
Requires-Dist: sqlalchemy[asyncio]>=2.0.44
Dynamic: license-file
